ulta/__init__.py
ulta/config.py
ulta/enum.py
ulta/infer.py
ulta/manager.py
ulta/model.py
ulta/py.typed
ulta/utils.py
ulta-0.2.0.dist-info/WHEEL
ulta-0.2.0.dist-info/METADATA
ulta-0.2.0.dist-info/RECORD
