Metadata-Version: 2.3
Name: ulta
Version: 0.2.0
Summary: Image Orientation Detection Library
Keywords: machine-learning,inference,image-processing,computer-vision,orientation-detection
Author: Muhammad Mominul Huque
Author-email: Muhammad Mominul Huque <mominul2082@gmail.com>
License: MIT
Classifier: Development Status :: 3 - Alpha
Classifier: Intended Audience :: Developers
Classifier: License :: OSI Approved :: MIT License
Classifier: Programming Language :: Python :: 3
Classifier: Programming Language :: Python :: 3.9
Classifier: Programming Language :: Python :: 3.10
Classifier: Programming Language :: Python :: 3.11
Classifier: Programming Language :: Python :: 3.12
Requires-Dist: numpy==1.26.4
Requires-Dist: pillow>=11.3.0
Requires-Dist: tensorboard>=2.20.0
Requires-Dist: torch>=2.8.0
Requires-Dist: torchvision>=0.23.0
Requires-Dist: requests>=2.31.0
Requires-Dist: tqdm>=4.66.0
Requires-Python: >=3.9
